app/addressbook.py
app/games_menu.py
app/information.py
app/logger.py
app/menu.py
app/notes.py
app/output.py
app/prompt_tool_ab.py
app/prompt_tool_nb.py
app/sort.py
app/games/hangman.py
app/games/magic_layer.py
Chatbot_by_IE-0.2.26.dist-info/LICENSE
Chatbot_by_IE-0.2.26.dist-info/METADATA
Chatbot_by_IE-0.2.26.dist-info/WHEEL
Chatbot_by_IE-0.2.26.dist-info/entry_points.txt
Chatbot_by_IE-0.2.26.dist-info/top_level.txt
Chatbot_by_IE-0.2.26.dist-info/RECORD
