Metadata-Version: 2.1
Name: Chatbot-by-IE
Version: 0.2.26
Summary: Chatbot: Addressbook, NoteBook, Sort file, Games
Home-page: https://github.com/Sanyavas/chatbot-team-project.git
Author: Oleksandr Vasylyna, Oleh Vakulchyk, Nataleia Orlovska, Anton Sokhnenko, Polina Dyka
Author-email: vasilinaoleksanrd@gmail.com
License: MIT
Classifier: Programming Language :: Python :: 3
Classifier: License :: OSI Approved :: MIT License
Classifier: Operating System :: OS Independent
License-File: LICENSE
Requires-Dist: prompt-toolkit
Requires-Dist: rarfile
Requires-Dist: prettytable
Requires-Dist: rich
